README
setup.py
bin/jsb3
bin/jsb3-fleet
bin/jsb3-irc
bin/jsb3-sleek
bin/jsb3-tornado
jsb3/__init__.py
jsb3/imports.py
jsb3/memcached.py
jsb3/version.py
jsb3.egg-info/PKG-INFO
jsb3.egg-info/SOURCES.txt
jsb3.egg-info/dependency_links.txt
jsb3.egg-info/not-zip-safe
jsb3.egg-info/top_level.txt
jsb3/contrib/__init__.py
jsb3/contrib/feedparser.py
jsb3/contrib/memcache.py
jsb3/contrib/rijndael.py
jsb3/contrib/sgmllib.py
jsb3/contrib/sgmllib3.py
jsb3/contrib/bs4/__init__.py
jsb3/contrib/bs4/dammit.py
jsb3/contrib/bs4/element.py
jsb3/contrib/bs4/testing.py
jsb3/contrib/bs4/builder/__init__.py
jsb3/contrib/bs4/builder/_html5lib.py
jsb3/contrib/bs4/builder/_htmlparser.py
jsb3/contrib/bs4/builder/_lxml.py
jsb3/contrib/sleekxmpp/__init__.py
jsb3/contrib/sleekxmpp/basexmpp.py
jsb3/contrib/sleekxmpp/clientxmpp.py
jsb3/contrib/sleekxmpp/componentxmpp.py
jsb3/contrib/sleekxmpp/exceptions.py
jsb3/contrib/sleekxmpp/version.py
jsb3/contrib/sleekxmpp/features/__init__.py
jsb3/contrib/sleekxmpp/features/feature_bind/__init__.py
jsb3/contrib/sleekxmpp/features/feature_bind/bind.py
jsb3/contrib/sleekxmpp/features/feature_bind/stanza.py
jsb3/contrib/sleekxmpp/features/feature_mechanisms/__init__.py
jsb3/contrib/sleekxmpp/features/feature_mechanisms/mechanisms.py
jsb3/contrib/sleekxmpp/features/feature_mechanisms/stanza/__init__.py
jsb3/contrib/sleekxmpp/features/feature_mechanisms/stanza/auth.py
jsb3/contrib/sleekxmpp/features/feature_mechanisms/stanza/challenge.py
jsb3/contrib/sleekxmpp/features/feature_mechanisms/stanza/failure.py
jsb3/contrib/sleekxmpp/features/feature_mechanisms/stanza/mechanisms.py
jsb3/contrib/sleekxmpp/features/feature_mechanisms/stanza/response.py
jsb3/contrib/sleekxmpp/features/feature_mechanisms/stanza/success.py
jsb3/contrib/sleekxmpp/features/feature_session/__init__.py
jsb3/contrib/sleekxmpp/features/feature_session/session.py
jsb3/contrib/sleekxmpp/features/feature_session/stanza.py
jsb3/contrib/sleekxmpp/features/feature_starttls/__init__.py
jsb3/contrib/sleekxmpp/features/feature_starttls/stanza.py
jsb3/contrib/sleekxmpp/features/feature_starttls/starttls.py
