Metadata-Version: 1.0
Name: jsb3
Version: 0.4.1
Summary: JSONBOT 3 on Python 3
Home-page: http://jsb3.googlecode.com/
Author: Bart Thate
Author-email: bthate@gmail.com
License: MIT
Download-URL: http://code.google.com/p/jsb3/downloads
Platform: UNKNOWN
Classifier: Development Status :: 3 - Alpha
Classifier: Environment :: Console
Classifier: Environment :: Other Environment
Classifier: Intended Audience :: Developers
Classifier: License :: OSI Approved :: MIT License
Classifier: Operating System :: Unix
Classifier: Programming Language :: Python
Classifier: Topic :: Communications :: Chat
Classifier: Topic :: Software Development :: Libraries :: Python Modules
